dinja2/__init__.py
dinja2/backend.py
dinja2/ext.py
dinja2/filters.py
dinja2-0.1.0.dist-info/DESCRIPTION.rst
dinja2-0.1.0.dist-info/METADATA
dinja2-0.1.0.dist-info/RECORD
dinja2-0.1.0.dist-info/WHEEL
dinja2-0.1.0.dist-info/metadata.json
dinja2-0.1.0.dist-info/top_level.txt
