Metadata-Version: 2.0
Name: dinja2
Version: 0.1.0
Summary: Jinja2 template backend for Django
Home-page: https://github.com/wooyek/dinja2
Author: Janusz Skonieczny
Author-email: js+pypi@bravelabs.pl
License: MIT
Keywords: dinja2
Platform: UNKNOWN
Classifier: Development Status :: 3 - Alpha
Classifier: Framework :: Django
Classifier: Framework :: Django :: 1.10
Classifier: Intended Audience :: Developers
Classifier: License :: OSI Approved :: BSD License
Classifier: Natural Language :: English
Classifier: Programming Language :: Python :: 2
Classifier: Programming Language :: Python :: 2.7
Classifier: Programming Language :: Python :: 3
Classifier: Programming Language :: Python :: 3.4
Classifier: Programming Language :: Python :: 3.5
Requires-Dist: Django (>=1.10)
Requires-Dist: django
